seamless_pdf/__init__.py
seamless_pdf/cli.py
seamless_pdf/converter.py
seamless_pdf/exceptions.py
seamless_pdf/html_converter.py
seamless_pdf/markdown_converter.py
seamless_pdf/utils.py
seamless_pdf-0.2.0.dist-info/licenses/LICENSE
seamless_pdf-0.2.0.dist-info/METADATA
seamless_pdf-0.2.0.dist-info/WHEEL
seamless_pdf-0.2.0.dist-info/entry_points.txt
seamless_pdf-0.2.0.dist-info/top_level.txt
seamless_pdf-0.2.0.dist-info/RECORD
