Metadata-Version: 2.4
Name: seamless-pdf
Version: 0.2.0
Summary: Convert HTML documents into continuous, single-page PDFs.
Author-email: Anthony Hua <tommyrobotics1@gmail.com>
License: MIT License
Requires-Python: >=3.10
License-File: LICENSE
Requires-Dist: playwright>=1.40.0
Requires-Dist: markdown>=3.10.1
Requires-Dist: Pygments>=2.17.0
Requires-Dist: pymdown-extensions>=10.0
Dynamic: license-file
